<?xml version="1.0"?>
<pnp:Provisioning xmlns:pnp="http://schemas.dev.office.com/PnP/2019/03/ProvisioningSchema">
  <pnp:Preferences Generator="OfficeDevPnP.Core, Version=3.9.1905.3, Culture=neutral, PublicKeyToken=5e633289e95c321a" />
  <pnp:Templates ID="CONTAINER-TEMPLATE-ROOT">
    <pnp:ProvisioningTemplate ID="TEMPLATE-ROOT" Scope="RootSite">
      <xi:include xmlns:xi="http://www.w3.org/2001/XInclude" href="Objects/Navigation.xml" />
      <xi:include xmlns:xi="http://www.w3.org/2001/XInclude" href="Objects/SiteFields.xml" />
      <xi:include xmlns:xi="http://www.w3.org/2001/XInclude" href="Objects/ContentTypes.xml" />
      <xi:include xmlns:xi="http://www.w3.org/2001/XInclude" href="Objects/Lists.xml" />
      <xi:include xmlns:xi="http://www.w3.org/2001/XInclude" href="Objects/Files.xml" />
      <xi:include xmlns:xi="http://www.w3.org/2001/XInclude" href="Objects/Features.xml" />
      <xi:include xmlns:xi="http://www.w3.org/2001/XInclude" href="Objects/WebSettings.xml" />
      <xi:include xmlns:xi="http://www.w3.org/2001/XInclude" href="Objects/Security.xml" />
    </pnp:ProvisioningTemplate>
  </pnp:Templates>
</pnp:Provisioning>